sintese.v
module sintese (
    input rst,
    input clk,
    input w,
    output z
);

    reg Y;
    parameter A = 1'b0, B = 1'b1;

    assign z = w & Y;

    always @(posedge clk or rst) begin
        if(rst == 1) Y <= A;
        else begin
            case(Y)
                A: if(w == 1) Y<=B;
                B: if(w == 0) Y<= A;
            endcase
        end
    end
    
endmodule

module testebench;
    reg rst0 = 0;
    reg clk0 = 0;
    reg w0 = 0;
    wire z0;

    sintese FSM(rst0, clk0, w0, z0);

    always #1 begin
        clk0 <= ~clk0;
    end

    initial begin
        $dumpvars;
        rst0 <= 1;
        w0 <= 0;
        #1
        rst0 <= 0;
        #2
        w0 <= 1;
        #2
        w0 <= 0;
        #2
        w0 <= 1;
        #4
        w0 <= 0;
        #2
        w0 <= 1;
        #7
        w0 <= 0;
        $finish;
    end
    
endmodule

dump.vcd
$date
	Mon Jul 12 14:15:13 2021
$end
$version
	Icarus Verilog
$end
$timescale
	1s
$end
$scope module testebench $end
$var wire 1 ! z0 $end
$var reg 1 " clk0 $end
$var reg 1 # rst0 $end
$var reg 1 $ w0 $end
$scope module FSM $end
$var wire 1 " clk $end
$var wire 1 # rst $end
$var wire 1 $ w $end
$var wire 1 ! z $end
$var reg 1 % Y $end
$upscope $end
$upscope $end
$enddefinitions $end
#0
$dumpvars
0%
0$
1#
0"
0!
$end
#1
0#
1"
#2
0"
#3
1!
1%
1"
1$
#4
0"
#5
0%
0!
1"
0$
#6
0"
#7
1!
1%
1"
1$
#8
0"
#9
1"
#10
0"
#11
0%
0!
1"
0$
#12
0"
#13
1!
1%
1"
1$
#14
0"
#15
1"
#16
0"
#17
1"
#18
0"
#19
1"
#20
0!
0"
0$
