analise.v
module analise (
    input rst,
    input clk,
    input ent,
    output y
);
reg Q0, Q1; // saidas do flip-flop
wire D0, D1;  // entradas do flip-flop

assign D0 = ent ^ Q0; // associando a porta logica ao wire
assign D1 = (~ent & Q1) + (ent & Q0 & ~Q1) + (ent & ~Q0 & Q1);
assign y = Q0 & Q1;

//funcionamento do flip-flop
always @(posedge clk or rst) begin
    if(rst == 1) begin
        Q0 <= 0;
        Q1 <= 0;
    end
    else begin
        Q0 = D0;
        Q1 = D1; 
    end
end
endmodule
//---------------------------------------------
module testebrench;
    reg ent0 = 0;
    reg rst0 = 0;
    reg clk0 = 0;
    wire y0;

    analise analise0(rst0, clk0, ent0, y0);

    initial begin
        $dumpvars;
        #1
        rst0 <= 1;
        #1
        rst0 <= 0;
        #1
        ent0 <= 1;
        clk0 <= 0;
        #1
        ent0 <= 1;
        clk0 <= 1;
        #1
        ent0 <= 1;
        clk0 <= 0;
        #2
        ent0 <= 1;
        clk0 <= 1;
        #1
        ent0 <= 1;
        clk0 <= 0;
        #2
        ent0 <= 1;
        clk0 <= 1;
        #1
        ent0 <= 0;
        clk0 <= 1;
        #2
        ent0 <= 1;
        clk0 <= 1;
        #1
        ent0 <= 1;
        clk0 <= 0;
        #2
        ent0 <= 1;
        clk0 <= 1;
        #1
        ent0 <= 1;
        clk0 <= 0;
        #1
        ent0 <= 0;
        clk0 <= 0;
        #1
        ent0 <= 0;
        clk0 <= 1;
        #1
        clk0 <= 0;
        #1
        $finish; 
    end
endmodule

dump.vcd
$date
	Mon Jul 12 12:27:14 2021
$end
$version
	Icarus Verilog
$end
$timescale
	1s
$end
$scope module testebrench $end
$var wire 1 ! y0 $end
$var reg 1 " clk0 $end
$var reg 1 # ent0 $end
$var reg 1 $ rst0 $end
$scope module analise0 $end
$var wire 1 % D0 $end
$var wire 1 " clk $end
$var wire 1 # ent $end
$var wire 1 $ rst $end
$var wire 1 ! y $end
$var wire 1 & D1 $end
$var reg 1 ' Q0 $end
$var reg 1 ( Q1 $end
$upscope $end
$upscope $end
$enddefinitions $end
#0
$dumpvars
x(
x'
x&
x%
0$
0#
0"
x!
$end
#1
0&
0!
0%
0(
0'
1$
#2
0$
#3
1%
1#
#4
1&
0%
1'
1"
#5
0"
#7
1&
1%
1(
0'
1"
#8
0"
#10
0&
1!
0%
1'
1"
#11
1&
1%
0#
#13
0&
0%
1#
#14
0"
#16
0!
1%
0(
0'
1"
#17
0"
#18
0%
0#
